sagbprojections/__init__.py
sagbprojections-0.0.5.dist-info/METADATA
sagbprojections-0.0.5.dist-info/WHEEL
sagbprojections-0.0.5.dist-info/top_level.txt
sagbprojections-0.0.5.dist-info/RECORD
