Metadata-Version: 2.1
Name: sagbprojections
Version: 0.0.5
Summary: A module to query SAGB NBA daily fantasy projections
Home-page: UNKNOWN
Author: Rohit Tanikella
Author-email: rohit.tanikella@gmail.com
License: MIT
Keywords: NBA
Platform: UNKNOWN
Classifier: Development Status :: 5 - Production/Stable
Classifier: Intended Audience :: Education
Classifier: Operating System :: Microsoft :: Windows :: Windows 10
Classifier: License :: OSI Approved :: MIT License
Classifier: Programming Language :: Python :: 3
Requires-Dist: pandas
